{"version": 0.6, "generator": "Overpass API 0.7.62.1 084b4234", "osm3s": {"timestamp_osm_base": "2024-11-04T13:53:06Z", "copyright": "The data included in this document is from www.openstreetmap.org. The data is made available under ODbL."}, "elements": [{"type": "node", "id": 771982523, "lat": 41.9923, "lon": 2.8181495}, {"type": "node", "id": 772093013, "lat": 41.9898397, "lon": 2.8193671}, {"type": "node", "id": 772143419, "lat": 41.9921285, "lon": 2.8179579}, {"type": "node", "id": 772169117, "lat": 41.9921004, "lon": 2.8181812}, {"type": "node", "id": 772204379, "lat": 41.9899482, "lon": 2.8193006}, {"type": "node", "id": 772240105, "lat": 41.9922849, "lon": 2.8179804, "tags": {"crossing": "marked", "crossing:markings": "zebra", "crossing_ref": "zebra", "highway": "crossing", "tactile_paving": "no"}}, {"type": "node", "id": 772244750, "lat": 41.9920853, "lon": 2.818238}, {"type": "node", "id": 773347289, "lat": 41.9921221, "lon": 2.8180667}, {"type": "node", "id": 3295050961, "lat": 41.9921259, "lon": 2.8180029, "tags": {"crossing": "marked", "crossing:markings": "zebra", "crossing_ref": "zebra", "highway": "crossing", "wheelchair": "yes"}}, {"type": "node", "id": 7093173396, "lat": 41.9922861, "lon": 2.8180644}, {"type": "node", "id": 7093173409, "lat": 41.992091, "lon": 2.8182087}, {"type": "node", "id": 7093173410, "lat": 41.989903, "lon": 2.8193235}, {"type": "node", "id": 7093173412, "lat": 41.9898676, "lon": 2.8193437}, {"type": "way", "id": 61944571, "nodes": [772204379, 7093173410, 7093173412, 772093013], "tags": {"cycleway:right": "track", "cycleway:right:oneway": "no", "hgv": "delivery", "highway": "secondary", "lanes": "2", "lit": "no", "local_code": "0476", "maxspeed": "20", "name": "Carrer del Pont de la Barca", "name:ca": "Carrer del Pont de la Barca", "oneway": "yes", "oneway:bicycle": "no", "ref": "N-IIa", "sidewalk:left": "yes", "sidewalk:left:surface": "paving_stones", "sidewalk:right": "separate", "smoothness": "good", "source": "Ajuntament de Girona", "surface": "asphalt"}}, {"type": "way", "id": 61944978, "nodes": [771982523, 7093173396, 772240105], "tags": {"cycleway:right": "track", "cycleway:right:oneway": "no", "highway": "secondary", "lanes": "1", "lit": "yes", "local_code": "0689", "maxspeed": "30", "name": "Rambla de Xavier Cugat", "name:ca": "Rambla de Xavier Cugat", "name:etymology:wikidata": "Q334180", "oneway": "yes", "oneway:bicycle": "no", "sidewalk:left": "no", "sidewalk:right": "separate", "smoothness": "good", "source": "Ajuntament de Girona", "surface": "asphalt"}}, {"type": "way", "id": 61947096, "nodes": [772143419, 3295050961, 773347289, 772169117], "tags": {"cycleway:right": "track", "cycleway:right:oneway": "no", "highway": "secondary", "lane_markings": "no", "lit": "yes", "local_code": "0689", "maxspeed": "30", "name": "Rambla de Xavier Cugat", "name:ca": "Rambla de Xavier Cugat", "name:etymology:wikidata": "Q334180", "oneway": "yes", "oneway:bicycle": "no", "sidewalk": "right", "sidewalk:right:surface": "paving_stones", "smoothness": "good", "source": "Ajuntament de Girona", "surface": "asphalt"}}, {"type": "way", "id": 764230135, "nodes": [772169117, 7093173409, 772244750], "tags": {"cycleway:right": "track", "cycleway:right:oneway": "no", "hgv": "delivery", "highway": "secondary", "junction": "roundabout", "lane_markings": "no", "lit": "yes", "local_code": "0887", "maxspeed": "30", "name": "Rotonda del Pont de la Barca", "name:ca": "Rotonda del Pont de la Barca", "oneway:bicycle": "no", "ref": "N-IIa", "sidewalk": "right", "sidewalk:right:surface": "paving_stones", "smoothness": "good", "source": "Ajuntament de Girona", "surface": "asphalt"}}]}